{"config":{"output_file":null,"full_docs":false,"pub_only":false,"reachable_only":false,"distro_crate":false,"signatures":false,"borrow_data":false},"version":"0.19.1","compilation":{"directory":"c:\\Users\\MB\\Source\\RUST\\The Rust Book\\The-Rust-Book\\minigrep","program":"C:\\Users\\MB\\.rustup\\toolchains\\stable-x86_64-pc-windows-msvc\\bin\\rls.exe","arguments":[],"output":"c:\\Users\\MB\\Source\\RUST\\The Rust Book\\The-Rust-Book\\minigrep\\target\\rls\\debug\\deps\\libminigrep-03ce06e420a24c42.rmeta"},"prelude":{"crate_id":{"name":"minigrep","disambiguator":[5360258614201110821,16084325958685958050]},"crate_root":"src","external_crates":[{"file_name":"c:\\Users\\MB\\Source\\RUST\\The Rust Book\\The-Rust-Book\\minigrep\\src\\main.rs","num":1,"id":{"name":"std","disambiguator":[902711862199739234,15082167224296373374]}},{"file_name":"c:\\Users\\MB\\Source\\RUST\\The Rust Book\\The-Rust-Book\\minigrep\\src\\main.rs","num":2,"id":{"name":"core","disambiguator":[5048311760381386034,12753961808535803278]}},{"file_name":"c:\\Users\\MB\\Source\\RUST\\The Rust Book\\The-Rust-Book\\minigrep\\src\\main.rs","num":3,"id":{"name":"compiler_builtins","disambiguator":[847775214756591688,12437863933651081164]}},{"file_name":"c:\\Users\\MB\\Source\\RUST\\The Rust Book\\The-Rust-Book\\minigrep\\src\\main.rs","num":4,"id":{"name":"rustc_std_workspace_core","disambiguator":[18098153966720408130,4102567439342721650]}},{"file_name":"c:\\Users\\MB\\Source\\RUST\\The Rust Book\\The-Rust-Book\\minigrep\\src\\main.rs","num":5,"id":{"name":"alloc","disambiguator":[14085577876822856882,15393158987199036233]}},{"file_name":"c:\\Users\\MB\\Source\\RUST\\The Rust Book\\The-Rust-Book\\minigrep\\src\\main.rs","num":6,"id":{"name":"libc","disambiguator":[3188366355873518403,14471389999965490426]}},{"file_name":"c:\\Users\\MB\\Source\\RUST\\The Rust Book\\The-Rust-Book\\minigrep\\src\\main.rs","num":7,"id":{"name":"unwind","disambiguator":[10237517513868340142,18396708545822173986]}},{"file_name":"c:\\Users\\MB\\Source\\RUST\\The Rust Book\\The-Rust-Book\\minigrep\\src\\main.rs","num":8,"id":{"name":"cfg_if","disambiguator":[17305999185247584930,14125623615750666193]}},{"file_name":"c:\\Users\\MB\\Source\\RUST\\The Rust Book\\The-Rust-Book\\minigrep\\src\\main.rs","num":9,"id":{"name":"hashbrown","disambiguator":[7451980452763147359,4800032867518142595]}},{"file_name":"c:\\Users\\MB\\Source\\RUST\\The Rust Book\\The-Rust-Book\\minigrep\\src\\main.rs","num":10,"id":{"name":"rustc_std_workspace_alloc","disambiguator":[842541340887862638,17591716377464122790]}},{"file_name":"c:\\Users\\MB\\Source\\RUST\\The Rust Book\\The-Rust-Book\\minigrep\\src\\main.rs","num":11,"id":{"name":"rustc_demangle","disambiguator":[14650435931294811010,18006816567319070280]}},{"file_name":"c:\\Users\\MB\\Source\\RUST\\The Rust Book\\The-Rust-Book\\minigrep\\src\\main.rs","num":12,"id":{"name":"std_detect","disambiguator":[16073749092757737146,5785406473963590530]}},{"file_name":"c:\\Users\\MB\\Source\\RUST\\The Rust Book\\The-Rust-Book\\minigrep\\src\\main.rs","num":13,"id":{"name":"panic_unwind","disambiguator":[9426002052484834533,14451905897035318657]}},{"file_name":"c:\\Users\\MB\\Source\\RUST\\The Rust Book\\The-Rust-Book\\minigrep\\src\\main.rs","num":14,"id":{"name":"minigrep","disambiguator":[3234353316749845548,224363758775089640]}},{"file_name":"c:\\Users\\MB\\Source\\RUST\\The Rust Book\\The-Rust-Book\\minigrep\\src\\main.rs","num":15,"id":{"name":"test","disambiguator":[2362059724671402708,10585270743624677136]}},{"file_name":"c:\\Users\\MB\\Source\\RUST\\The Rust Book\\The-Rust-Book\\minigrep\\src\\main.rs","num":16,"id":{"name":"getopts","disambiguator":[2148500613115993165,6430017358201395089]}},{"file_name":"c:\\Users\\MB\\Source\\RUST\\The Rust Book\\The-Rust-Book\\minigrep\\src\\main.rs","num":17,"id":{"name":"rustc_std_workspace_std","disambiguator":[17223780013770788073,14494721823926434216]}},{"file_name":"c:\\Users\\MB\\Source\\RUST\\The Rust Book\\The-Rust-Book\\minigrep\\src\\main.rs","num":18,"id":{"name":"unicode_width","disambiguator":[7203033763437606119,4191258238539543586]}},{"file_name":"c:\\Users\\MB\\Source\\RUST\\The Rust Book\\The-Rust-Book\\minigrep\\src\\main.rs","num":19,"id":{"name":"term","disambiguator":[13248425952572553216,10500048093320884310]}}],"span":{"file_name":"src\\main.rs","byte_start":0,"byte_end":650,"line_start":1,"line_end":19,"column_start":1,"column_end":2}},"imports":[{"kind":"Use","ref_id":{"krate":1,"index":2131},"span":{"file_name":"src\\main.rs","byte_start":9,"byte_end":12,"line_start":1,"line_end":1,"column_start":10,"column_end":13},"alias_span":null,"name":"env","value":"","parent":{"krate":0,"index":0}},{"kind":"Use","ref_id":{"krate":2,"index":23},"span":{"file_name":"src\\main.rs","byte_start":9,"byte_end":12,"line_start":1,"line_end":1,"column_start":10,"column_end":13},"alias_span":null,"name":"env","value":"","parent":{"krate":0,"index":0}},{"kind":"Use","ref_id":{"krate":1,"index":6172},"span":{"file_name":"src\\main.rs","byte_start":23,"byte_end":30,"line_start":2,"line_end":2,"column_start":10,"column_end":17},"alias_span":null,"name":"process","value":"","parent":{"krate":0,"index":0}},{"kind":"Use","ref_id":{"krate":14,"index":12},"span":{"file_name":"src\\main.rs","byte_start":47,"byte_end":53,"line_start":4,"line_end":4,"column_start":15,"column_end":21},"alias_span":null,"name":"Config","value":"","parent":{"krate":0,"index":0}}],"defs":[{"kind":"Mod","id":{"krate":0,"index":0},"span":{"file_name":"src\\main.rs","byte_start":0,"byte_end":650,"line_start":1,"line_end":19,"column_start":1,"column_end":2},"name":"","qualname":"::","value":"src\\main.rs","parent":null,"children":[{"krate":0,"index":1},{"krate":0,"index":2},{"krate":0,"index":3},{"krate":0,"index":4},{"krate":0,"index":6},{"krate":0,"index":9},{"krate":0,"index":12},{"krate":0,"index":14}],"decl_id":null,"docs":"","sig":null,"attributes":[]},{"kind":"Function","id":{"krate":0,"index":12},"span":{"file_name":"src\\main.rs","byte_start":59,"byte_end":63,"line_start":6,"line_end":6,"column_start":4,"column_end":8},"name":"main","qualname":"::main","value":"fn main()","parent":null,"children":[],"decl_id":null,"docs":"","sig":null,"attributes":[{"value":"allow(dead_code)","span":{"file_name":"src\\main.rs","byte_start":0,"byte_end":0,"line_start":1,"line_end":1,"column_start":1,"column_end":1}}]},{"kind":"Local","id":{"krate":0,"index":3791650828},"span":{"file_name":"src\\main.rs","byte_start":155,"byte_end":161,"line_start":9,"line_end":9,"column_start":9,"column_end":15},"name":"config","qualname":"config$HirId { owner: DefId(0:12 ~ minigrep[4a63]::main), local_id: 71 }","value":"minigrep::Config","parent":null,"children":[],"decl_id":null,"docs":"","sig":null,"attributes":[]},{"kind":"Local","id":{"krate":0,"index":805306380},"span":{"file_name":"src\\main.rs","byte_start":205,"byte_end":208,"line_start":9,"line_end":9,"column_start":59,"column_end":62},"name":"err","qualname":"$HirId { owner: DefId(0:12 ~ minigrep[4a63]::main), local_id: 68 }::err","value":"&str","parent":null,"children":[],"decl_id":null,"docs":"","sig":null,"attributes":[]},{"kind":"Local","id":{"krate":0,"index":704643084},"span":{"file_name":"src\\main.rs","byte_start":361,"byte_end":362,"line_start":14,"line_end":14,"column_start":16,"column_end":17},"name":"e","qualname":"e$HirId { owner: DefId(0:12 ~ minigrep[4a63]::main), local_id: 84 }","value":"std::boxed::Box<dyn std::error::Error>","parent":null,"children":[],"decl_id":null,"docs":"","sig":null,"attributes":[]}],"impls":[],"refs":[{"kind":"Mod","span":{"file_name":"src\\main.rs","byte_start":4,"byte_end":7,"line_start":1,"line_end":1,"column_start":5,"column_end":8},"ref_id":{"krate":1,"index":0}},{"kind":"Mod","span":{"file_name":"src\\main.rs","byte_start":18,"byte_end":21,"line_start":2,"line_end":2,"column_start":5,"column_end":8},"ref_id":{"krate":1,"index":0}},{"kind":"Mod","span":{"file_name":"src\\main.rs","byte_start":37,"byte_end":45,"line_start":4,"line_end":4,"column_start":5,"column_end":13},"ref_id":{"krate":14,"index":0}},{"kind":"Function","span":{"file_name":"src\\main.rs","byte_start":189,"byte_end":203,"line_start":9,"line_end":9,"column_start":43,"column_end":57},"ref_id":{"krate":2,"index":8227}},{"kind":"Function","span":{"file_name":"src\\main.rs","byte_start":172,"byte_end":175,"line_start":9,"line_end":9,"column_start":26,"column_end":29},"ref_id":{"krate":14,"index":17}},{"kind":"Type","span":{"file_name":"src\\main.rs","byte_start":164,"byte_end":170,"line_start":9,"line_end":9,"column_start":18,"column_end":24},"ref_id":{"krate":14,"index":12}},{"kind":"Function","span":{"file_name":"src\\main.rs","byte_start":181,"byte_end":185,"line_start":9,"line_end":9,"column_start":35,"column_end":39},"ref_id":{"krate":1,"index":2230}},{"kind":"Mod","span":{"file_name":"src\\main.rs","byte_start":176,"byte_end":179,"line_start":9,"line_end":9,"column_start":30,"column_end":33},"ref_id":{"krate":1,"index":2131}},{"kind":"Variable","span":{"file_name":"src\\main.rs","byte_start":264,"byte_end":267,"line_start":10,"line_end":10,"column_start":53,"column_end":56},"ref_id":{"krate":0,"index":805306380}},{"kind":"Function","span":{"file_name":"src\\main.rs","byte_start":328,"byte_end":332,"line_start":11,"line_end":11,"column_start":18,"column_end":22},"ref_id":{"krate":1,"index":6398}},{"kind":"Mod","span":{"file_name":"src\\main.rs","byte_start":319,"byte_end":326,"line_start":11,"line_end":11,"column_start":9,"column_end":16},"ref_id":{"krate":1,"index":6172}},{"kind":"Function","span":{"file_name":"src\\main.rs","byte_start":376,"byte_end":379,"line_start":14,"line_end":14,"column_start":31,"column_end":34},"ref_id":{"krate":14,"index":18}},{"kind":"Mod","span":{"file_name":"src\\main.rs","byte_start":366,"byte_end":374,"line_start":14,"line_end":14,"column_start":21,"column_end":29},"ref_id":{"krate":14,"index":0}},{"kind":"Variable","span":{"file_name":"src\\main.rs","byte_start":380,"byte_end":386,"line_start":14,"line_end":14,"column_start":35,"column_end":41},"ref_id":{"krate":0,"index":3791650828}},{"kind":"Type","span":{"file_name":"src\\main.rs","byte_start":357,"byte_end":360,"line_start":14,"line_end":14,"column_start":12,"column_end":15},"ref_id":{"krate":2,"index":40082}},{"kind":"Type","span":{"file_name":"src\\main.rs","byte_start":357,"byte_end":360,"line_start":14,"line_end":14,"column_start":12,"column_end":15},"ref_id":{"krate":2,"index":40082}},{"kind":"Variable","span":{"file_name":"src\\main.rs","byte_start":612,"byte_end":613,"line_start":15,"line_end":15,"column_start":45,"column_end":46},"ref_id":{"krate":0,"index":704643084}},{"kind":"Function","span":{"file_name":"src\\main.rs","byte_start":634,"byte_end":638,"line_start":17,"line_end":17,"column_start":18,"column_end":22},"ref_id":{"krate":1,"index":6398}},{"kind":"Mod","span":{"file_name":"src\\main.rs","byte_start":625,"byte_end":632,"line_start":17,"line_end":17,"column_start":9,"column_end":16},"ref_id":{"krate":1,"index":6172}}],"macro_refs":[],"relations":[]}